LICENSE
MANIFEST.in
README.md
setup.py
docs/index.md
epic_theme/__init__.py
epic_theme/apps.py
epic_theme/version.py
epic_theme.egg-info/PKG-INFO
epic_theme.egg-info/SOURCES.txt
epic_theme.egg-info/dependency_links.txt
epic_theme.egg-info/requires.txt
epic_theme.egg-info/top_level.txt
epic_theme/static/epic_admin/css/main.css
epic_theme/static/epic_admin/css/main.css.map
epic_theme/static/epic_admin/css/vendors~main.css
epic_theme/static/epic_admin/css/vendors~main.css.map
epic_theme/static/epic_admin/fonts/materialdesignicons-webfont.666e135393ac4ac62ae551b9fb0985ae.eot
epic_theme/static/epic_admin/fonts/materialdesignicons-webfont.815a2673d08221fb4968f19e59a14f2e.woff2
epic_theme/static/epic_admin/fonts/materialdesignicons-webfont.875141d94aca807fbf74f7f53fa98a26.woff
epic_theme/static/epic_admin/fonts/materialdesignicons-webfont.f558fb5cc12a31989a7e4048b4fba71a.ttf
epic_theme/static/epic_admin/js/main.js
epic_theme/static/epic_admin/js/main.js.map
epic_theme/static/epic_admin/js/vendors~main.js
epic_theme/static/epic_admin/js/vendors~main.js.map
epic_theme/templates/admin/app_index.html
epic_theme/templates/admin/base.html
epic_theme/templates/admin/base_site.html
epic_theme/templates/admin/change_list.html
epic_theme/templates/admin/change_list_object_tools.html
epic_theme/templates/admin/login.html
epic_theme/templates/admin/parts/app_menu.html
epic_theme/templates/admin/parts/custom_menu.html
epic_theme/templates/admin/widgets/app_list.html
epic_theme/templates/admin/widgets/chartjs.html